LICENSE.txt
MANIFEST.in
README.md
setup.py
SPLASH/__init__.py
SPLASH/_version.py
SPLASH/network_utils.py
SPLASH/pipeline.py
SPLASH/rf_registry.py
SPLASH/trained_models/V2_best_sed_model.pkl
SPLASH/trained_models/V2_host_prop_best_model.pkl
SPLASH/trained_models/__init__.py
SPLASH/trained_models/host_prop_nn_abs_mag.pkl
SPLASH/trained_models/knn_imputers_new_version.pkl
SPLASH/trained_models/knn_imputers_old_version.pkl
SPLASH/trained_models/rf_registry.pkl
astro_SPLASH.egg-info/PKG-INFO
astro_SPLASH.egg-info/SOURCES.txt
astro_SPLASH.egg-info/dependency_links.txt
astro_SPLASH.egg-info/requires.txt
astro_SPLASH.egg-info/top_level.txt
unit_tests/__init__.py
unit_tests/test_pipeline.py
unit_tests/utils.py